muhaftab_demo_package/__init__.py
muhaftab_demo_package/engine.py
muhaftab_demo_package-0.0.4.dist-info/LICENSE
muhaftab_demo_package-0.0.4.dist-info/METADATA
muhaftab_demo_package-0.0.4.dist-info/WHEEL
muhaftab_demo_package-0.0.4.dist-info/top_level.txt
muhaftab_demo_package-0.0.4.dist-info/RECORD
