Metadata-Version: 2.1
Name: muhaftab-demo-package
Version: 0.0.4
Summary: A demo package for learning purpose
Home-page: UNKNOWN
Author: Muhammad Aftab
Author-email: muhaftabkhan@gmail.com
License: UNKNOWN
Platform: UNKNOWN
Classifier: Programming Language :: Python :: 3
Classifier: License :: OSI Approved :: MIT License
Classifier: Operating System :: OS Independent
Requires-Python: >=3.6
Requires-Dist: confluent-kafka (==1.2.0)
